hatch_pre_index/.published_version
hatch_pre_index/__init__.py
hatch_pre_index/hooks.py
hatch_pre_index/pre_index_publisher.py
hatch_pre_index/utils.py
hatch_pre_index-1.0.1.dist-info/METADATA
hatch_pre_index-1.0.1.dist-info/WHEEL
hatch_pre_index-1.0.1.dist-info/entry_points.txt
hatch_pre_index-1.0.1.dist-info/licenses/LICENSE
hatch_pre_index-1.0.1.dist-info/RECORD
