Metadata-Version: 2.4
Name: hatch-pre-index
Version: 1.0.1
Summary: A publisher for hatch to check the project version and to run scripts before it invokes the index publisher.
Project-URL: Homepage, https://github.com/krokoreit/hatch-pre-index
Project-URL: Source Code, https://github.com/krokoreit/hatch-pre-index
Author-email: krokoreit <krokoreit@gmail.com>
License-Expression: MIT
License-File: LICENSE
Keywords: Python,before index,hatch,publish
Classifier: Framework :: Hatch
Classifier: Operating System :: OS Independent
Classifier: Programming Language :: Python :: 3
Requires-Python: >=3.10
Requires-Dist: click
Requires-Dist: keyring
